proxa/__init__.py
proxa/core.py
proxa/ip_info.py
proxa/proxy.py
proxa/utils.py
proxa-1.0.1.dist-info/licenses/LICENSE
proxa-1.0.1.dist-info/METADATA
proxa-1.0.1.dist-info/WHEEL
proxa-1.0.1.dist-info/top_level.txt
proxa-1.0.1.dist-info/RECORD
