Metadata-Version: 2.4
Name: proxa
Version: 1.0.1
Summary: A simple yet powerful proxy management library for Python
Author-email: Abbas Bachari <abbas-bachari@hotmail.com>
License: MIT
Project-URL: Homepage, https://github.com/abbas-bachari/proxa
Project-URL: Repository, https://github.com/abbas-bachari/proxa
Requires-Python: >=3.8
License-File: LICENSE
Requires-Dist: requests>=2.31.0
Dynamic: license-file
